LICENSE
README.rst
setup.py
koala_fastapi_common/__init__.py
koala_fastapi_common/base_model.py
koala_fastapi_common/base_repository.py
koala_fastapi_common/base_schema.py
koala_fastapi_common/custom_exception.py
koala_fastapi_common/database.py
koala_fastapi_common/exception.py
koala_fastapi_common/logger.py
koala_fastapi_common/response_model.py
koala_fastapi_common/security.py
koala_fastapi_common.egg-info/PKG-INFO
koala_fastapi_common.egg-info/SOURCES.txt
koala_fastapi_common.egg-info/dependency_links.txt
koala_fastapi_common.egg-info/requires.txt
koala_fastapi_common.egg-info/top_level.txt